deformation_models/__init__.py
deformation_models/_version.py
deformation_models/_version.pyi
deformation_models/main.py
deformation_models/py.typed
deformation_models/tests/test_models.py
deformation_models/tests/test_package.py
deformation_models-0.0.2.dist-info/licenses/LICENSE
deformation_models-0.0.2.dist-info/METADATA
deformation_models-0.0.2.dist-info/WHEEL
deformation_models-0.0.2.dist-info/top_level.txt
deformation_models-0.0.2.dist-info/RECORD
