Metadata-Version: 2.4
Name: deformation_models
Version: 0.0.2
Summary: Phenomenological deformation models
Author-email: Chris Havlin <chris.havlin@gmail.com>
License: BSD 3-Clause License
Project-URL: Homepage, https://github.com/iSTRUM/deformation_models
Project-URL: Bug Tracker, https://github.com/iSTRUM/deformation_models/issues
Project-URL: Discussions, https://github.com/iSTRUM/deformation_models/discussions
Project-URL: Changelog, https://github.com/iSTRUM/deformation_models/releases
Classifier: Development Status :: 1 - Planning
Classifier: Intended Audience :: Science/Research
Classifier: Intended Audience :: Developers
Classifier: License :: OSI Approved :: BSD License
Classifier: Operating System :: OS Independent
Classifier: Programming Language :: Python
Classifier: Programming Language :: Python :: 3
Classifier: Programming Language :: Python :: 3 :: Only
Classifier: Programming Language :: Python :: 3.9
Classifier: Programming Language :: Python :: 3.10
Classifier: Programming Language :: Python :: 3.11
Classifier: Programming Language :: Python :: 3.12
Classifier: Programming Language :: Python :: 3.13
Classifier: Topic :: Scientific/Engineering
Requires-Python: >=3.9
License-File: LICENSE
Requires-Dist: numpy
Requires-Dist: scipy
Provides-Extra: test
Requires-Dist: pytest>=6; extra == "test"
Requires-Dist: pytest-cov>=3; extra == "test"
Provides-Extra: dev
Requires-Dist: pytest>=6; extra == "dev"
Requires-Dist: pytest-cov>=3; extra == "dev"
Provides-Extra: docs
Requires-Dist: sphinx>=7.0; extra == "docs"
Requires-Dist: myst_parser>=0.13; extra == "docs"
Requires-Dist: sphinx_copybutton; extra == "docs"
Requires-Dist: sphinx_autodoc_typehints; extra == "docs"
Requires-Dist: furo>=2023.08.17; extra == "docs"
Provides-Extra: examples
Requires-Dist: pyleoclim; extra == "examples"
Requires-Dist: jupyterlab; extra == "examples"
Dynamic: license-file
